backend_pheflux/backend_pheflux/__init__.py
backend_pheflux/backend_pheflux/asgi.py
backend_pheflux/backend_pheflux/settings.py
backend_pheflux/backend_pheflux/urls.py
backend_pheflux/backend_pheflux/wsgi.py
backend_pheflux/db.sqlite3
backend_pheflux/manage.py
backend_pheflux/userprofile/__init__.py
backend_pheflux/userprofile/admin.py
backend_pheflux/userprofile/api.py
backend_pheflux/userprofile/apps.py
backend_pheflux/userprofile/migrations/0001_initial.py
backend_pheflux/userprofile/migrations/__init__.py
backend_pheflux/userprofile/models.py
backend_pheflux/userprofile/schemas.py
backend_pheflux/userprofile/serializers.py
backend_pheflux/userprofile/tests.py
backend_pheflux/userprofile/tokens.py
backend_pheflux/userprofile/urls.py
backend_pheflux/userprofile/views.py
backend_pheflux-0.1.0.dist-info/METADATA
backend_pheflux-0.1.0.dist-info/WHEEL
backend_pheflux-0.1.0.dist-info/RECORD
