Metadata-Version: 2.1
Name: backend-pheflux
Version: 0.1.0
Summary: 
Author: pineiden
Author-email: dpineda@uchile.cl
Requires-Python: >=3.11,<4.0
Classifier: Programming Language :: Python :: 3
Classifier: Programming Language :: Python :: 3.11
Classifier: Programming Language :: Python :: 3.12
Requires-Dist: django (>=5.1,<6.0)
Requires-Dist: django-extensions (>=3.2.3,<4.0.0)
Requires-Dist: django-ninja (>=1.3.0,<2.0.0)
Requires-Dist: django-phonenumber-field[phonenumbers] (>=8.0.0,<9.0.0)
Requires-Dist: djangorestframework (>=3.15.2,<4.0.0)
Requires-Dist: rich (>=13.7.1,<14.0.0)
Requires-Dist: six (>=1.16.0,<2.0.0)
Requires-Dist: ujson (>=5.10.0,<6.0.0)
